Metadata-Version: 2.4
Name: dopo
Version: 0.0.3
Summary: A framework for Detecting Outliers in Premise LCA Operations (DOPO)
Author-email: Caro Friedberger <caroline.friedberger@gmail.com>, Romain Sacchi <romain.sacchi@psi.ch>
Maintainer-email: Caro Friedberger <caroline.friedberger@gmail.com>, Romain Sacchi <romain.sacchi@psi.ch>
Project-URL: source, https://github.com/Laboratory-for-Energy-Systems-Analysis/dopo
Project-URL: homepage, https://github.com/Laboratory-for-Energy-Systems-Analysis/dopo
Project-URL: tracker, https://github.com/Laboratory-for-Energy-Systems-Analysis/dopo/issues
Classifier: Development Status :: 4 - Beta
Classifier: Programming Language :: Python
Classifier: Programming Language :: Python :: 3
Classifier: Programming Language :: Python :: 3.10
Classifier: Programming Language :: Python :: 3.11
Classifier: Programming Language :: Python :: 3.12
Classifier: Natural Language :: English
Classifier: Operating System :: OS Independent
Classifier: Topic :: Scientific/Engineering
Requires-Python: >=3.10
License-File: LICENSE
Requires-Dist: dash_bootstrap_components
Requires-Dist: dash_daq
Requires-Dist: numpy<2.0.0
Requires-Dist: openpyxl
Requires-Dist: pandas
Requires-Dist: plotly
Requires-Dist: pytest
Requires-Dist: PyYAML
Requires-Dist: tabulate
Provides-Extra: testing
Requires-Dist: dopo; extra == "testing"
Requires-Dist: pytest; extra == "testing"
Requires-Dist: pytest-cov; extra == "testing"
Requires-Dist: python-coveralls; extra == "testing"
Provides-Extra: dev
Requires-Dist: build; extra == "dev"
Requires-Dist: pre-commit; extra == "dev"
Requires-Dist: pylint; extra == "dev"
Requires-Dist: pytest; extra == "dev"
Requires-Dist: pytest-cov; extra == "dev"
Requires-Dist: pytest-randomly; extra == "dev"
Requires-Dist: setuptools; extra == "dev"
Dynamic: license-file
